smartrandom/__init__.py
smartrandom/generators.py
smartrandom-0.3.1.dist-info/licenses/LICENSE
smartrandom-0.3.1.dist-info/METADATA
smartrandom-0.3.1.dist-info/WHEEL
smartrandom-0.3.1.dist-info/top_level.txt
smartrandom-0.3.1.dist-info/RECORD
