Metadata-Version: 2.4
Name: smartrandom
Version: 0.3.1
Summary: Random data generators. Allows you to generate random strings of a given length from letters, numbers and symbols, as well as randomize text. Helps generate passwords, service codes (for example, for sending via SMS), hashes and much more. Generates smart, recoverable passwords.
Home-page: https://github.com/smartlegionlab/smartrandom/
Author: A.A. Suvorov
Author-email: smartlegiondev@gmail.com
License: BSD 3-Clause License
Project-URL: Documentation, https://github.com/smartlegionlab/smartrandom/blob/master/README.md
Project-URL: Release notes, https://github.com/smartlegionlab/smartrandom/releases
Keywords: password generator,code generator,random generator,random code generator,random string generator,random bytes generator,text randomizer,smartrandom,smartlegionlab,A.A Suvorov
Classifier: Development Status :: 5 - Production/Stable
Classifier: License :: OSI Approved :: BSD License
Classifier: Natural Language :: English
Classifier: Operating System :: OS Independent
Classifier: Operating System :: POSIX :: Linux
Classifier: Programming Language :: Python :: 3 :: Only
Classifier: Topic :: Software Development :: Libraries :: Python Modules
Requires-Python: >=3.6
License-File: LICENSE
Dynamic: license-file
